README.rst
setup.cfg
setup.py
aliasdict/__init__.py
aliasdict/aliasdict.py
aliasdict/version.py
aliasdict.egg-info/PKG-INFO
aliasdict.egg-info/SOURCES.txt
aliasdict.egg-info/dependency_links.txt
aliasdict.egg-info/top_level.txt