Metadata-Version: 1.1
Name: aliasdict
Version: 0.9.5
Summary: a dict that supports alias of KEY
Home-page: https://bitbucket.org/yokoshin/aliasdict
Author: yokoshin
Author-email: yokoshin719@yahoo.co.jp
License: UNKNOWN
Platform: UNKNOWN
Classifier: Development Status :: 5 - Production/Stable
Classifier: Intended Audience :: Developers
Classifier: License :: OSI Approved :: MIT License
Classifier: Programming Language :: Python :: 3.5
Classifier: Programming Language :: Python :: 3.6
Classifier: Programming Language :: Python :: 3.7
